{
  "tradesCount": 2,
  "trades": [
    {
      "id": "4c88acdf-78c3-439e-80ac-6c4cae4387d9",
      "pool_type": "scalping",
      "date": "2022-01-21T20:32:00+00:00",
      "pair": "usdt",
      "direction": "long",
      "margin": 100,
      "leverage": 4,
      "size": 400,
      "fee": 800,
      "pnl": 12,
      "result": "win",
      "created_at": "2026-02-17T21:02:14.423718+00:00"
    },
    {
      "id": "511f3fbc-a658-4282-9c98-dbfde5f4fa5f",
      "pool_type": "scalping",
      "date": "2026-02-17T21:09:18.35+00:00",
      "pair": "usdt",
      "direction": "long",
      "margin": 0,
      "leverage": 19,
      "size": 0,
      "fee": 0,
      "pnl": 0,
      "result": "lose",
      "created_at": "2026-02-17T21:09:18.876588+00:00"
    }
  ],
  "investorsCount": 3,
  "investors": [
    {
      "id": "ef45110a-2e05-4da1-8018-64e83fd9b7e5",
      "pool_type": "scalping",
      "wallet_address": "0xseedinvestor1",
      "investor_name": "Seed Investor (Crypto)",
      "invested_amount": 5000,
      "duration_months": null,
      "investment_end_date": null,
      "deposit_transactions": [],
      "created_at": "2026-02-17T20:52:07.061063+00:00",
      "updated_at": "2026-02-17T20:52:07.061063+00:00"
    },
    {
      "id": "4f975e2a-385f-4e48-9744-467bc3eb6f2d",
      "pool_type": "scalping",
      "wallet_address": "0x508d61ad3f1559679bfae3942508b4cf7767935a",
      "investor_name": null,
      "invested_amount": 0,
      "duration_months": null,
      "investment_end_date": null,
      "deposit_transactions": [
        {
          "date": "2026-02-17T20:56:06.034721+00:00",
          "amount": 0.01,
          "tx_hash": "0x088c56752abfb086105b27f716ba6c23922be013cdd95dac1b30494ceacc9916"
        },
        {
          "date": "2026-02-17T21:05:37.910802+00:00",
          "amount": 0.01,
          "tx_hash": "0x40575d478005210e0909ae86ab82cc4089928044e61bf62a66e7da08dbb45403"
        }
      ],
      "created_at": "2026-02-17T20:56:06.034721+00:00",
      "updated_at": "2026-02-17T21:05:37.910802+00:00"
    },
    {
      "id": "db5e2ea3-a278-4139-a66d-7de895ebc50b",
      "pool_type": "scalping",
      "wallet_address": "0xe24487c9c697fa4613a20706c67bf3372074e8ab",
      "investor_name": null,
      "invested_amount": 0.01,
      "duration_months": null,
      "investment_end_date": null,
      "deposit_transactions": [
        {
          "date": "2026-02-20T08:58:25.341376+00:00",
          "amount": 0.01,
          "tx_hash": "0xbe1213eb3c879c33233c06bcd3532d5dd65489ef87fb9750fe6fd46379dae88a",
          "intent_id": "3b9ccbd1-db02-4c87-8eda-be7b08d01ec5"
        }
      ],
      "created_at": "2026-02-20T08:58:25.341376+00:00",
      "updated_at": "2026-02-20T08:58:25.341376+00:00"
    }
  ]
}